roop/__init__.py
roop/capturer.py
roop/core.py
roop/face_analyser.py
roop/face_reference.py
roop/globals.py
roop/metadata.py
roop/typing.py
roop/utilities.py
roop/processors/__init__.py
roop/processors/frame/__init__.py
roop/processors/frame/core.py
roop/processors/frame/face_enhancer.py
roop/processors/frame/face_swapper.py
roop_pip-1.0.0.dist-info/LICENSE
roop_pip-1.0.0.dist-info/METADATA
roop_pip-1.0.0.dist-info/WHEEL
roop_pip-1.0.0.dist-info/dependency_links.txt
roop_pip-1.0.0.dist-info/entry_points.txt
roop_pip-1.0.0.dist-info/top_level.txt
roop_pip-1.0.0.dist-info/RECORD
