Metadata-Version: 2.1
Name: roop-pip
Version: 1.0.0
Summary: One-click face swap
Home-page: https://github.com/Konohamaru04/roop-pip
Author: Amartya Deshmukh
Author-email: dedsec.konohamaru@gmail.com
Classifier: Programming Language :: Python :: 3
Classifier: License :: OSI Approved :: MIT License
Classifier: Operating System :: OS Independent
Requires-Python: >=3.10
License-File: LICENSE
Requires-Dist: numpy ==1.24.3
Requires-Dist: opencv-python ==4.8.0.74
Requires-Dist: onnx ==1.14.0
Requires-Dist: insightface ==0.7.3
Requires-Dist: psutil ==5.9.5
Requires-Dist: tk ==0.1.0
Requires-Dist: customtkinter ==5.2.0
Requires-Dist: pillow ==10.0.0
Requires-Dist: tensorflow ==2.13.0
Requires-Dist: opennsfw2 ==0.10.2
Requires-Dist: protobuf ==4.23.4
Requires-Dist: tqdm ==4.65.0
Requires-Dist: gfpgan ==1.3.8
Requires-Dist: onnxruntime ==1.15.1 ; python_version != "3.9" and sys_platform == "darwin" and platform_machine != "arm64"
Requires-Dist: onnxruntime-coreml ==1.13.1 ; python_version == "3.9" and sys_platform == "darwin" and platform_machine == "arm64"
Requires-Dist: onnxruntime-gpu ==1.15.1 ; sys_platform != "darwin"
Requires-Dist: tkinterdnd2 ==0.3.0 ; sys_platform != "darwin" and platform_machine != "arm64"
Requires-Dist: tkinterdnd2-universal ==1.7.3 ; sys_platform == "darwin" and platform_machine == "arm64"
Requires-Dist: onnxruntime-silicon ==1.13.1 ; sys_platform == "darwin" and platform_machine == "arm64"
